wecom_sdk/__init__.py
wecom_sdk/agent.py
wecom_sdk/corgroup.py
wecom_sdk/efficiency.py
wecom_sdk/external_contact.py
wecom_sdk/invoice.py
wecom_sdk/media.py
wecom_sdk/message.py
wecom_sdk/oa.py
wecom_sdk/oauth2.py
wecom_sdk/pay.py
wecom_sdk/base/__init__.py
wecom_sdk/base/callback.py
wecom_sdk/base/client.py
wecom_sdk/base/crypt.py
wecom_sdk/base/exception.py
wecom_sdk/base/mixin.py
wecom_sdk/contact/__init__.py
wecom_sdk/contact/client.py
wecom_sdk/contact/department.py
wecom_sdk/contact/tag.py
wecom_sdk/contact/user.py
wecom_sdk/service/__init__.py
wecom_sdk/service/client.py
wecom_sdk_py-0.1.0.dist-info/LICENSE
wecom_sdk_py-0.1.0.dist-info/METADATA
wecom_sdk_py-0.1.0.dist-info/WHEEL
wecom_sdk_py-0.1.0.dist-info/top_level.txt
wecom_sdk_py-0.1.0.dist-info/RECORD
