Metadata-Version: 2.1
Name: wecom-sdk-py
Version: 0.1.0
Summary: 企业微信Python服务端SDK
Author: QuantTide Inc.
Author-email: tech@quanttide.com
License: Apache 2.0
License-File: LICENSE
Requires-Dist: requests
Requires-Dist: xmltodict
Requires-Dist: pycryptodome
